pipelinetest/__init__.py
pipelinetest/app.py
pipelinetest-0.1.0.dist-info/WHEEL
pipelinetest-0.1.0.dist-info/METADATA
pipelinetest-0.1.0.dist-info/RECORD
