Metadata-Version: 2.1
Name: pipelinetest
Version: 0.1.0
Summary: 
Author: cltj
Author-email: tj@cloudlink.ai
Requires-Python: >=3.8,<4.0
Classifier: Programming Language :: Python :: 3
Classifier: Programming Language :: Python :: 3.10
Classifier: Programming Language :: Python :: 3.8
Classifier: Programming Language :: Python :: 3.9
Requires-Dist: requests (>=2.28.2,<3.0.0)
